<?xml version="1.0" encoding="utf-8"?>
<CoverageReport scope="Summary">
  <Summary>
    <Generatedon>03-04-2023 - 13:27:18</Generatedon>
    <Parser>MultiReportParser (10x OpenCoverParser)</Parser>
    <Assemblies>2</Assemblies>
    <Classes>52</Classes>
    <Files>102</Files>
    <Coveredlines>1554</Coveredlines>
    <Uncoveredlines>1743</Uncoveredlines>
    <Coverablelines>3297</Coverablelines>
    <Totallines>3587</Totallines>
    <Linecoverage>47.1</Linecoverage>
    <Coveredbranches>0</Coveredbranches>
    <Totalbranches>0</Totalbranches>
    <Coveredmethods>280</Coveredmethods>
    <Totalmethods>585</Totalmethods>
    <Methodcoverage>47.8</Methodcoverage>
  </Summary>
  <Coverage>
    <Assembly name="PlaymodeTests" classes="11" coverage="66.3" coveredlines="915" coverablelines="1380" totallines="1336" branchcoverage="" coveredbranches="0" totalbranches="0" coveredmethods="175" totalmethods="266" methodcoverage="65.7">
      <Class name="AvatarModificationRoomTests" coverage="86.7" coveredlines="276" coverablelines="318" totallines="328" branchcoverage="" coveredbranches="0" totalbranches="0" coveredmethods="71" totalmethods="79" methodcoverage="89.8" />
      <Class name="AvatarRoomTests" coverage="70.8" coveredlines="318" coverablelines="449" totallines="259" branchcoverage="" coveredbranches="0" totalbranches="0" coveredmethods="43" totalmethods="65" methodcoverage="66.1" />
      <Class name="DatabasePlayModeTests" coverage="35.2" coveredlines="24" coverablelines="68" totallines="79" branchcoverage="" coveredbranches="0" totalbranches="0" coveredmethods="4" totalmethods="8" methodcoverage="50" />
      <Class name="ExternalAPITests" coverage="54.5" coveredlines="12" coverablelines="22" totallines="27" branchcoverage="" coveredbranches="0" totalbranches="0" coveredmethods="2" totalmethods="4" methodcoverage="50" />
      <Class name="LoginScreenTests" coverage="53.8" coveredlines="56" coverablelines="104" totallines="204" branchcoverage="" coveredbranches="0" totalbranches="0" coveredmethods="10" totalmethods="20" methodcoverage="50" />
      <Class name="MainMenuTests" coverage="0" coveredlines="0" coverablelines="3" totallines="13" branchcoverage="" coveredbranches="0" totalbranches="0" coveredmethods="0" totalmethods="2" methodcoverage="0" />
      <Class name="MultiplayerTests" coverage="46.1" coveredlines="6" coverablelines="13" totallines="29" branchcoverage="" coveredbranches="0" totalbranches="0" coveredmethods="1" totalmethods="2" methodcoverage="50" />
      <Class name="RoomCreationMenuTests" coverage="54.9" coveredlines="94" coverablelines="171" totallines="144" branchcoverage="" coveredbranches="0" totalbranches="0" coveredmethods="17" totalmethods="34" methodcoverage="50" />
      <Class name="RoomSelectionMenuTests" coverage="39" coveredlines="39" coverablelines="100" totallines="92" branchcoverage="" coveredbranches="0" totalbranches="0" coveredmethods="8" totalmethods="20" methodcoverage="40" />
      <Class name="SettingsMenuTests" coverage="57.1" coveredlines="52" coverablelines="91" totallines="92" branchcoverage="" coveredbranches="0" totalbranches="0" coveredmethods="13" totalmethods="26" methodcoverage="50" />
      <Class name="WhiteboardTest" coverage="92.6" coveredlines="38" coverablelines="41" totallines="69" branchcoverage="" coveredbranches="0" totalbranches="0" coveredmethods="6" totalmethods="6" methodcoverage="100" />
    </Assembly>
    <Assembly name="Scripts" classes="41" coverage="33.3" coveredlines="639" coverablelines="1917" totallines="2268" branchcoverage="" coveredbranches="0" totalbranches="0" coveredmethods="105" totalmethods="319" methodcoverage="32.9">
      <Class name="APIHelper" coverage="58.3" coveredlines="7" coverablelines="12" totallines="19" branchcoverage="" coveredbranches="0" totalbranches="0" coveredmethods="1" totalmethods="2" methodcoverage="50" />
      <Class name="AudioDectection" coverage="44.6" coveredlines="46" coverablelines="103" totallines="137" branchcoverage="" coveredbranches="0" totalbranches="0" coveredmethods="8" totalmethods="15" methodcoverage="53.3" />
      <Class name="AvatarModificationButtonBehaviour" coverage="0" coveredlines="0" coverablelines="8" totallines="20" branchcoverage="" coveredbranches="0" totalbranches="0" coveredmethods="0" totalmethods="2" methodcoverage="0" />
      <Class name="AvatarModificationMenuLineRender" coverage="100" coveredlines="49" coverablelines="49" totallines="44" branchcoverage="" coveredbranches="0" totalbranches="0" coveredmethods="6" totalmethods="6" methodcoverage="100" />
      <Class name="AvatarModificationMenuScript" coverage="33.5" coveredlines="100" coverablelines="298" totallines="306" branchcoverage="" coveredbranches="0" totalbranches="0" coveredmethods="14" totalmethods="39" methodcoverage="35.8" />
      <Class name="BuildCommand" coverage="0" coveredlines="0" coverablelines="297" totallines="288" branchcoverage="" coveredbranches="0" totalbranches="0" coveredmethods="0" totalmethods="30" methodcoverage="0" />
      <Class name="CameraTargettingScript" coverage="50" coveredlines="39" coverablelines="78" totallines="68" branchcoverage="" coveredbranches="0" totalbranches="0" coveredmethods="6" totalmethods="11" methodcoverage="54.5" />
      <Class name="CommonMenuScript" coverage="64.2" coveredlines="9" coverablelines="14" totallines="21" branchcoverage="" coveredbranches="0" totalbranches="0" coveredmethods="2" totalmethods="4" methodcoverage="50" />
      <Class name="ConnectPlayer" coverage="3.9" coveredlines="2" coverablelines="51" totallines="66" branchcoverage="" coveredbranches="0" totalbranches="0" coveredmethods="1" totalmethods="4" methodcoverage="25" />
      <Class name="DatabaseManager" coverage="0" coveredlines="0" coverablelines="88" totallines="103" branchcoverage="" coveredbranches="0" totalbranches="0" coveredmethods="0" totalmethods="24" methodcoverage="0" />
      <Class name="DragObject" coverage="0" coveredlines="0" coverablelines="12" totallines="27" branchcoverage="" coveredbranches="0" totalbranches="0" coveredmethods="0" totalmethods="3" methodcoverage="0" />
      <Class name="FootstepBehaviour" coverage="0" coveredlines="0" coverablelines="18" totallines="27" branchcoverage="" coveredbranches="0" totalbranches="0" coveredmethods="0" totalmethods="4" methodcoverage="0" />
      <Class name="FootstepBehaviourAnimator" coverage="0" coveredlines="0" coverablelines="16" totallines="21" branchcoverage="" coveredbranches="0" totalbranches="0" coveredmethods="0" totalmethods="4" methodcoverage="0" />
      <Class name="GetExternalAPIData" coverage="0" coveredlines="0" coverablelines="7" totallines="16" branchcoverage="" coveredbranches="0" totalbranches="0" coveredmethods="0" totalmethods="2" methodcoverage="0" />
      <Class name="GlobalAudioSettings" coverage="30.7" coveredlines="4" coverablelines="13" totallines="18" branchcoverage="" coveredbranches="0" totalbranches="0" coveredmethods="2" totalmethods="6" methodcoverage="33.3" />
      <Class name="GlobalGameSettings" coverage="78.5" coveredlines="11" coverablelines="14" totallines="19" branchcoverage="" coveredbranches="0" totalbranches="0" coveredmethods="1" totalmethods="2" methodcoverage="50" />
      <Class name="GlobalGameStrings" coverage="0" coveredlines="0" coverablelines="10" totallines="12" branchcoverage="" coveredbranches="0" totalbranches="0" coveredmethods="0" totalmethods="4" methodcoverage="0" />
      <Class name="INIFile" coverage="63.1" coveredlines="12" coverablelines="19" totallines="39" branchcoverage="" coveredbranches="0" totalbranches="0" coveredmethods="4" totalmethods="5" methodcoverage="80" />
      <Class name="LoginMenuScript" coverage="35.4" coveredlines="17" coverablelines="48" totallines="48" branchcoverage="" coveredbranches="0" totalbranches="0" coveredmethods="4" totalmethods="8" methodcoverage="50" />
      <Class name="LoginResponse" coverage="0" coveredlines="0" coverablelines="4" totallines="17" branchcoverage="" coveredbranches="0" totalbranches="0" coveredmethods="0" totalmethods="8" methodcoverage="0" />
      <Class name="LoginSceneInitialization" coverage="0" coveredlines="0" coverablelines="59" totallines="70" branchcoverage="" coveredbranches="0" totalbranches="0" coveredmethods="0" totalmethods="2" methodcoverage="0" />
      <Class name="MainMenuScript" coverage="6" coveredlines="4" coverablelines="66" totallines="79" branchcoverage="" coveredbranches="0" totalbranches="0" coveredmethods="2" totalmethods="22" methodcoverage="9" />
      <Class name="ModCameraScript" coverage="29.6" coveredlines="24" coverablelines="81" totallines="51" branchcoverage="" coveredbranches="0" totalbranches="0" coveredmethods="6" totalmethods="8" methodcoverage="75" />
      <Class name="PlayerEmoticonHandler" coverage="70.5" coveredlines="48" coverablelines="68" totallines="59" branchcoverage="" coveredbranches="0" totalbranches="0" coveredmethods="12" totalmethods="22" methodcoverage="54.5" />
      <Class name="PlayerManager" coverage="0" coveredlines="0" coverablelines="6" totallines="18" branchcoverage="" coveredbranches="0" totalbranches="0" coveredmethods="0" totalmethods="4" methodcoverage="0" />
      <Class name="PlayerMovementScript" coverage="50.7" coveredlines="72" coverablelines="142" totallines="99" branchcoverage="" coveredbranches="0" totalbranches="0" coveredmethods="6" totalmethods="9" methodcoverage="66.6" />
      <Class name="RESPONSE" coverage="0" coveredlines="0" coverablelines="2" totallines="17" branchcoverage="" coveredbranches="0" totalbranches="0" coveredmethods="0" totalmethods="4" methodcoverage="0" />
      <Class name="RoomCreationMenuScript" coverage="57.8" coveredlines="11" coverablelines="19" totallines="28" branchcoverage="" coveredbranches="0" totalbranches="0" coveredmethods="3" totalmethods="6" methodcoverage="50" />
      <Class name="RoomSelectionMenuScript" coverage="41.3" coveredlines="12" coverablelines="29" totallines="32" branchcoverage="" coveredbranches="0" totalbranches="0" coveredmethods="4" totalmethods="12" methodcoverage="33.3" />
      <Class name="SavingPanelBehaviour" coverage="8.1" coveredlines="3" coverablelines="37" totallines="59" branchcoverage="" coveredbranches="0" totalbranches="0" coveredmethods="1" totalmethods="7" methodcoverage="14.2" />
      <Class name="SavWav" coverage="73.2" coveredlines="74" coverablelines="101" totallines="175" branchcoverage="" coveredbranches="0" totalbranches="0" coveredmethods="4" totalmethods="7" methodcoverage="57.1" />
      <Class name="ScaleFromAudioClip" coverage="11.1" coveredlines="2" coverablelines="18" totallines="31" branchcoverage="" coveredbranches="0" totalbranches="0" coveredmethods="1" totalmethods="6" methodcoverage="16.6" />
      <Class name="ScaleFromMicrophone" coverage="66.6" coveredlines="12" coverablelines="18" totallines="31" branchcoverage="" coveredbranches="0" totalbranches="0" coveredmethods="4" totalmethods="6" methodcoverage="66.6" />
      <Class name="StopShakingHands" coverage="0" coveredlines="0" coverablelines="5" totallines="11" branchcoverage="" coveredbranches="0" totalbranches="0" coveredmethods="0" totalmethods="2" methodcoverage="0" />
      <Class name="StopSitToStand" coverage="57.1" coveredlines="4" coverablelines="7" totallines="14" branchcoverage="" coveredbranches="0" totalbranches="0" coveredmethods="1" totalmethods="2" methodcoverage="50" />
      <Class name="StopStandToSit" coverage="72.7" coveredlines="8" coverablelines="11" totallines="14" branchcoverage="" coveredbranches="0" totalbranches="0" coveredmethods="2" totalmethods="3" methodcoverage="66.6" />
      <Class name="StopWaving" coverage="0" coveredlines="0" coverablelines="5" totallines="11" branchcoverage="" coveredbranches="0" totalbranches="0" coveredmethods="0" totalmethods="2" methodcoverage="0" />
      <Class name="TextCameraLookAt" coverage="55.5" coveredlines="5" coverablelines="9" totallines="16" branchcoverage="" coveredbranches="0" totalbranches="0" coveredmethods="1" totalmethods="2" methodcoverage="50" />
      <Class name="User" coverage="55.5" coveredlines="5" coverablelines="9" totallines="11" branchcoverage="" coveredbranches="0" totalbranches="0" coveredmethods="1" totalmethods="2" methodcoverage="50" />
      <Class name="Whiteboard" coverage="90.9" coveredlines="20" coverablelines="22" totallines="39" branchcoverage="" coveredbranches="0" totalbranches="0" coveredmethods="4" totalmethods="4" methodcoverage="100" />
      <Class name="WhiteboardMarker" coverage="88.6" coveredlines="39" coverablelines="44" totallines="87" branchcoverage="" coveredbranches="0" totalbranches="0" coveredmethods="4" totalmethods="4" methodcoverage="100" />
    </Assembly>
  </Coverage>
</CoverageReport>